{"meta":{"name":"VOD AVENTURA","id":"TV-Prime58","type":"channel","posterShape":"landscape","videos":[{"id":"TV-Primestream_58_0","title":"127 horas (2010)"},{"id":"TV-Primestream_58_1","title":"Marea letal (2012)"},{"id":"TV-Primestream_58_2","title":"Beethoven: Aventura de navidad (2011)"},{"id":"TV-Primestream_58_3","title":"Blancanieves y la leyenda del cazador (2012)"},{"id":"TV-Primestream_58_4","title":"En tiempo de brujas (2011)"},{"id":"TV-Primestream_58_5","title":"Camino a la libertad (2010)"},{"id":"TV-Primestream_58_6","title":"Circo del Sol: Mundos Lejanos (2012)"},{"id":"TV-Primestream_58_7","title":" el robosapien (2013)"},{"id":"TV-Primestream_58_8","title":"El aprendiz de brujo (2010)"},{"id":"TV-Primestream_58_9","title":"El extraordinario viaje de T.S. Spivet (2013)"},{"id":"TV-Primestream_58_10","title":"El inventor de juegos (2014)"},{"id":"TV-Primestream_58_11","title":"Infierno blanco (2011)"},{"id":"TV-Primestream_58_12","title":"El Llanero Solitario (2013)"},{"id":"TV-Primestream_58_13","title":"El séptimo hijo (2014)"},{"id":"TV-Primestream_58_14","title":" el último guerrero (2010)"},{"id":"TV-Primestream_58_15","title":"Ga'Hoole: La leyenda de los guardianes (2010)"},{"id":"TV-Primestream_58_16","title":"Jack (1996)"},{"id":"TV-Primestream_58_17","title":"La invención de Hugo (2011)"},{"id":"TV-Primestream_58_18","title":"¡Piratas! (2011)"},{"id":"TV-Primestream_58_19","title":"La legión del águila (2011)"},{"id":"TV-Primestream_58_20","title":"Dora y la ciudad perdida (2019)"},{"id":"TV-Primestream_58_21","title":"Las aventuras de Tintín: El secreto del unicornio (2011)"},{"id":"TV-Primestream_58_22","title":"Tierra a Eco (2014)"},{"id":"TV-Primestream_58_23","title":"Los juegos del hambre (2012)"},{"id":"TV-Primestream_58_24","title":" un mundo de fantasía (2013)"},{"id":"TV-Primestream_58_25","title":"Paladin (2011)"},{"id":"TV-Primestream_58_26","title":"Peste Negra (1992)"},{"id":"TV-Primestream_58_27","title":"Pompeya (2012)"},{"id":"TV-Primestream_58_28","title":"Regreso a la isla de Nim (2013)"},{"id":"TV-Primestream_58_29","title":"Scooby-Doo! Misterio en la lucha libre (2014)"},{"id":"TV-Primestream_58_30","title":"The Gold Retrievers (2009)"},{"id":"TV-Primestream_58_31","title":"En busca de Santa Can (2010)"},{"id":"TV-Primestream_58_32","title":"Cuando todo está perdido (2013)"},{"id":"TV-Primestream_58_33","title":"Una aventura extraordinaria (2012)"},{"id":"TV-Primestream_58_34","title":"Un monstruo viene a verme (2016)"},{"id":"TV-Primestream_58_35","title":"Misión rescate (1992)"},{"id":"TV-Primestream_58_36","title":"El aprendiz de brujo (2010)"},{"id":"TV-Primestream_58_37","title":"Hombres de negro II (2002)"},{"id":"TV-Primestream_58_38","title":"Peter Rabbit (2018)"},{"id":"TV-Primestream_58_39","title":"Robots. La invasión (2015)"},{"id":"TV-Primestream_58_40","title":"Santa Claus 2 (2002)"},{"id":"TV-Primestream_58_41","title":"Los 4 fantásticos y Silver Surfer (2007)"},{"id":"TV-Primestream_58_42","title":"Los juegos del hambre: En llamas (2013)"},{"id":"TV-Primestream_58_43","title":"Mi gran amigo Joe (1998)"},{"id":"TV-Primestream_58_44","title":"Piratas del mar Caribe (1942)"},{"id":"TV-Primestream_58_45","title":"El Mago de Oz (1985)"},{"id":"TV-Primestream_58_46","title":"Brimstone. La hija del predicador (2016)"},{"id":"TV-Primestream_58_47","title":"Mi monstruo y yo (2007)"},{"id":"TV-Primestream_58_48","title":"Animales fantásticos y dónde encontrarlos (2016)"},{"id":"TV-Primestream_58_49","title":"Piratas del mar Caribe (1942)"},{"id":"TV-Primestream_58_50","title":"Van Helsing (2004)"},{"id":"TV-Primestream_58_51","title":"La leyenda del Zorro (2005)"},{"id":"TV-Primestream_58_52","title":"Cazafantasmas (2016)"},{"id":"TV-Primestream_58_53","title":"Ataque a los Titanes (2015)"},{"id":"TV-Primestream_58_54","title":"La invención de Hugo (2011)"},{"id":"TV-Primestream_58_55","title":"La vida de Pi (2012)"},{"id":"TV-Primestream_58_56","title":"Ninja Turtles: Fuera de las sombras (2016)"},{"id":"TV-Primestream_58_57","title":"Los 4 fantásticos (2005)"},{"id":"TV-Primestream_58_58","title":"El séptimo hijo (2014)"},{"id":"TV-Primestream_58_59","title":"Surviving The Wild (2018)"},{"id":"TV-Primestream_58_60","title":"La momia: La tumba del emperador Dragón (2008)"},{"id":"TV-Primestream_58_61","title":"Stardust (2007)"},{"id":"TV-Primestream_58_62","title":"King Kong (2005)"},{"id":"TV-Primestream_58_63","title":"Sleepy Hollow (1999)"},{"id":"TV-Primestream_58_64","title":"La caperucita roja (1959)"},{"id":"TV-Primestream_58_65","title":"Cocodrilo Dundee II (1988)"},{"id":"TV-Primestream_58_66","title":"Robin Hood (2018)"},{"id":"TV-Primestream_58_67","title":"Aliens Ate My Homework (2018)"},{"id":"TV-Primestream_58_68","title":"The Christmas Dragon (2014)"},{"id":"TV-Primestream_58_69","title":"En el corazón del mar (2015)"},{"id":"TV-Primestream_58_70","title":"El hombre de la máscara de hierro (1998)"},{"id":"TV-Primestream_58_71","title":"El rey Escorpión (2002)"},{"id":"TV-Primestream_58_72","title":"The Do-Over (2016)"},{"id":"TV-Primestream_58_73","title":"Tomb Raider 2 (2021)"},{"id":"TV-Primestream_58_74","title":"Diablo (2016)"},{"id":"TV-Primestream_58_75","title":"El corredor del laberinto: La cura mortal (2018)"},{"id":"TV-Primestream_58_76","title":"Ocean's Thirteen (2007)"},{"id":"TV-Primestream_58_77","title":"La gran aventura de Winter el delfín (2011)"},{"id":"TV-Primestream_58_78","title":"Karate Kid III. El desafío final (1989)"},{"id":"TV-Primestream_58_79","title":"En tiempo de brujas (2011)"},{"id":"TV-Primestream_58_80","title":"Tomorrowland: El mundo del mañana (2015)"},{"id":"TV-Primestream_58_81","title":"Los juegos del hambre: Sinsajo. Parte 2 (2015)"},{"id":"TV-Primestream_58_82","title":"Cazafantasmas (2016)"},{"id":"TV-Primestream_58_83","title":"El extraordinario viaje de Lucius Dumb (2013)"},{"id":"TV-Primestream_58_84","title":"Turbo Kid (2015)"},{"id":"TV-Primestream_58_85","title":"La vida secreta de Walter Mitty (1947)"},{"id":"TV-Primestream_58_86","title":"El corredor del laberinto (2014)"},{"id":"TV-Primestream_58_87","title":"Piratas del mar Caribe (1942)"},{"id":"TV-Primestream_58_88","title":"Arma joven (1988)"},{"id":"TV-Primestream_58_89","title":"Labyrinth (1959)"},{"id":"TV-Primestream_58_90","title":"Ira de titanes (2012)"},{"id":"TV-Primestream_58_91","title":"Destino de caballero (2001)"},{"id":"TV-Primestream_58_92","title":"The Salvation (2014)"},{"id":"TV-Primestream_58_93","title":"Dragonheart (Corazón de dragón) (1996)"},{"id":"TV-Primestream_58_94","title":"El valle de la venganza (2016)"},{"id":"TV-Primestream_58_95","title":"El rey Escorpión (2002)"},{"id":"TV-Primestream_58_96","title":"Hombres de negro II (2002)"},{"id":"TV-Primestream_58_97","title":"Ocean's Eleven. Hagan juego (2001)"},{"id":"TV-Primestream_58_98","title":"Cargo (2017)"},{"id":"TV-Primestream_58_99","title":"Ben-Hur (2016)"},{"id":"TV-Primestream_58_100","title":"Indiana Jones 5 (2022)"},{"id":"TV-Primestream_58_101","title":"Tomb Raider (2018)"},{"id":"TV-Primestream_58_102","title":"El rey Escorpión (2002)"},{"id":"TV-Primestream_58_103","title":"El corredor del laberinto: Las pruebas (2015)"},{"id":"TV-Primestream_58_104","title":"Acapulo la vida va (2017)"},{"id":"TV-Primestream_58_105","title":"Estasis (2017)"},{"id":"TV-Primestream_58_106","title":"Jo Pil-Ho: El despertar de la rabia (2019)"},{"id":"TV-Primestream_58_107","title":"El niño que pudo ser rey (2019)"},{"id":"TV-Primestream_58_108","title":"Piratas del mar Caribe (1942)"},{"id":"TV-Primestream_58_109","title":"La Leyenda del Rey Mono: El Regreso del Héroe (2015)"},{"id":"TV-Primestream_58_110","title":"El único (2001)"},{"id":"TV-Primestream_58_111","title":"Camino a Marte (2017)"},{"id":"TV-Primestream_58_112","title":"Crónicas de Navidad (2018)"},{"id":"TV-Primestream_58_113","title":"Mongol (2007)"},{"id":"TV-Primestream_58_114","title":"El rey Escorpión (2002)"},{"id":"TV-Primestream_58_115","title":"G.I. Joe: La venganza (2013)"},{"id":"TV-Primestream_58_116","title":"The Black Sea (2015)"},{"id":"TV-Primestream_58_117","title":"Liberad a Willy (1993)"},{"id":"TV-Primestream_58_118","title":"La última jugada (2018)"},{"id":"TV-Primestream_58_119","title":"El Hombre Sin Gravedad (2019)"},{"id":"TV-Primestream_58_120","title":"Las crónicas de Blancanieves: El cazador y la reina del hielo (2016)"},{"id":"TV-Primestream_58_121","title":"Cazafantasmas (2016)"},{"id":"TV-Primestream_58_122","title":"Los juegos del hambre: Sinsajo. Parte 1 (2014)"},{"id":"TV-Primestream_58_123","title":"Max 2: El héroe de la Casa Blanca (2017)"},{"id":"TV-Primestream_58_124","title":"Drones (2013)"},{"id":"TV-Primestream_58_125","title":"Fabricated City (2017)"},{"id":"TV-Primestream_58_126","title":"Límite vertical (2000)"},{"id":"TV-Primestream_58_127","title":"Monster Hunt 2 (2018)"},{"id":"TV-Primestream_58_128","title":"Los juegos del hambre (2012)"},{"id":"TV-Primestream_58_129","title":"Jasón y los argonautas (1963)"},{"id":"TV-Primestream_58_130","title":"Animales fantásticos: los crímenes de Grindelwald (2018)"},{"id":"TV-Primestream_58_131","title":"Santa Claus 3: Por una Navidad sin frío (2006)"},{"id":"TV-Primestream_58_132","title":"Abyss (1989)"},{"id":"TV-Primestream_58_133","title":"Percy Jackson y el mar de los monstruos (2013)"},{"id":"TV-Primestream_58_134","title":"Ocean's Twelve (2004)"},{"id":"TV-Primestream_58_135","title":"Independence Day: Contraataque (2016)"},{"id":"TV-Primestream_58_136","title":"Liberad a Willy (1993)"},{"id":"TV-Primestream_58_137","title":"Viaje al centro de la Tierra (2008)"},{"id":"TV-Primestream_58_138","title":"Parque Jurásico (1993)"},{"id":"TV-Primestream_58_139","title":"La búsqueda 2: El diario secreto (2007)"},{"id":"TV-Primestream_58_140","title":"Cowboys & Aliens (2011)"},{"id":"TV-Primestream_58_141","title":"R.I.P.D. Departamento de Policía Mortal (2013)"},{"id":"TV-Primestream_58_142","title":"Rescate al amanecer (2006)"},{"id":"TV-Primestream_58_143","title":"Star Trek (2009)"},{"id":"TV-Primestream_58_144","title":"El imperio del fuego (2002)"},{"id":"TV-Primestream_58_145","title":"John Carter (2012)"},{"id":"TV-Primestream_58_146","title":"En el bosque (2016)"},{"id":"TV-Primestream_58_147","title":"Los Goonies (1985)"},{"id":"TV-Primestream_58_148","title":" el último guerrero (2010)"},{"id":"TV-Primestream_58_149","title":"Vampiros: Sed de Sangre (2004)"},{"id":"TV-Primestream_58_150","title":"A la caza de los ñumanos (2016)"},{"id":"TV-Primestream_58_151","title":"Maléfica (2014)"},{"id":"TV-Primestream_58_152","title":"Descifrando el enigma (1980)"},{"id":"TV-Primestream_58_153","title":"Eragon (2006)"},{"id":"TV-Primestream_58_154","title":"El rey escorpión: el libro de las almas (2018)"},{"id":"TV-Primestream_58_155","title":"Mojin: The Lost Legend (2015)"},{"id":"TV-Primestream_58_156","title":"Cuando todo está perdido (2013)"},{"id":"TV-Primestream_58_157","title":"Un golpe sobrenatural (2018)"},{"id":"TV-Primestream_58_158","title":"Viaje al centro de la Tierra 2: La isla misteriosa (2012)"},{"id":"TV-Primestream_58_159","title":"La Odisea de los Giles (2019)"},{"id":"TV-Primestream_58_160","title":"Halo: Nightfall (2014)"},{"id":"TV-Primestream_58_161","title":"Percy Jackson y el ladrón del rayo (2010)"},{"id":"TV-Primestream_58_162","title":"Los ángeles de Charlie: Al límite (2003)"},{"id":"TV-Primestream_58_163","title":"Ready Player One (2018)"},{"id":"TV-Primestream_58_164","title":"Catwoman (2004)"},{"id":"TV-Primestream_58_165","title":"Swiss Army Man (2016)"},{"id":"TV-Primestream_58_166","title":"Pesadillas (2015)"},{"id":"TV-Primestream_58_167","title":"Kingsman: Servicio secreto (2014)"},{"id":"TV-Primestream_58_168","title":"Los reyes del crimen (2001)"},{"id":"TV-Primestream_58_169","title":"Liberad a Willy 2 (1995)"},{"id":"TV-Primestream_58_170","title":"El laberinto del fauno (2006)"},{"id":"TV-Primestream_58_171","title":"El secreto de los hermanos Grimm (2005)"},{"id":"TV-Primestream_58_172","title":"La quinta ola (2016)"},{"id":"TV-Primestream_58_173","title":"Cazadores de sombras: Ciudad de hueso (2013)"},{"id":"TV-Primestream_58_174","title":"I Am Santa Claus (2014)"},{"id":"TV-Primestream_58_175","title":"The Mummy Returns (El regreso de la momia) (2001)"},{"id":"TV-Primestream_58_176","title":"Remi: Una aventura extraordinaria (2019)"},{"id":"TV-Primestream_58_177","title":"La venganza del conde de Montecristo (2002)"},{"id":"TV-Primestream_58_178","title":"Thelma y Louise (1991)"},{"id":"TV-Primestream_58_179","title":"Indiana Jones 5 (2022)"},{"id":"TV-Primestream_58_180","title":"Mowgli: La leyenda de la selva (2018)"},{"id":"TV-Primestream_58_181","title":"El llanero solitario (2003)"},{"id":"TV-Primestream_58_182","title":"La búsqueda (National Treasure) (2004)"},{"id":"TV-Primestream_58_183","title":"Mad Max: Salvajes de autopista (1979)"},{"id":"TV-Primestream_58_184","title":"127 horas (2010)"},{"id":"TV-Primestream_58_185","title":"Intrépidos forajidos: Arma Joven II (1990)"},{"id":"TV-Primestream_58_186","title":"Hardcore Henry (2015)"},{"id":"TV-Primestream_58_187","title":"Sin frenos (2012)"},{"id":"TV-Primestream_58_188","title":"La serie Divergente: Insurgente (2015)"},{"id":"TV-Primestream_58_189","title":"Heidi (2015)"},{"id":"TV-Primestream_58_190","title":"El atlas de las nubes (2012)"},{"id":"TV-Primestream_58_191","title":"Mad Max 2: El guerrero de la carretera (1981)"},{"id":"TV-Primestream_58_192","title":"13 asesinos (2010)"},{"id":"TV-Primestream_58_193","title":"Bailando con lobos (1990)"},{"id":"TV-Primestream_58_194","title":"Exodus: Dioses y reyes (2014)"},{"id":"TV-Primestream_58_195","title":"El nuevo Karate Kid (1994)"},{"id":"TV-Primestream_58_196","title":"La brújula dorada (2007)"},{"id":"TV-Primestream_58_197","title":"Keyla (2017)"},{"id":"TV-Primestream_58_198","title":"Pan: Viaje a Nunca Jamás (2015)"},{"id":"TV-Primestream_58_199","title":"Ngai sing (2016)"},{"id":"TV-Primestream_58_200","title":"El día de mañana (2004)"},{"id":"TV-Primestream_58_201","title":"Gangster Squad: Brigada de élite (2013)"},{"id":"TV-Primestream_58_202","title":"Apocalypto (2006)"},{"id":"TV-Primestream_58_203","title":"Berlin Falling (2017)"},{"id":"TV-Primestream_58_204","title":"La gran aventura de Winter el delfín 2 (2014)"},{"id":"TV-Primestream_58_205","title":"El último gran héroe (1993)"},{"id":"TV-Primestream_58_206","title":"Indiana Jones 5 (2022)"},{"id":"TV-Primestream_58_207","title":"Tomorrowland: El mundo del mañana (2015)"},{"id":"TV-Primestream_58_208","title":"Lara Croft: Tomb Raider (2001)"},{"id":"TV-Primestream_58_209","title":"Hércules: El origen de la leyenda (2014)"},{"id":"TV-Primestream_58_210","title":"Mad Max 3: Más allá de la cúpula del trueno (1985)"},{"id":"TV-Primestream_58_211","title":"Hombres de negro II (2002)"},{"id":"TV-Primestream_58_212","title":"Las crónicas de Narnia: La travesía del viajero del alba (2010)"},{"id":"TV-Primestream_58_213","title":"Las crónicas de Narnia: El príncipe Caspian (2008)"},{"id":"TV-Primestream_58_214","title":"Divergente (2014)"},{"id":"TV-Primestream_58_215","title":"Baywatch: Los vigilantes de la playa (2017)"},{"id":"TV-Primestream_58_216","title":"Eraser (Eliminador) (1996)"},{"id":"TV-Primestream_58_217","title":"Abigail y la ciudad perdida (2019)"},{"id":"TV-Primestream_58_218","title":"Bernie el Delfín (2018)"},{"id":"TV-Primestream_58_219","title":" la historia continúa (1986)"},{"id":"TV-Primestream_58_220","title":"Braven (El Leñador) (2018)"},{"id":"TV-Primestream_58_221","title":"Piratas del mar Caribe (1942)"},{"id":"TV-Primestream_58_222","title":"Mia y el león blanco (2018)"},{"id":"TV-Primestream_58_223","title":"Mortal engines (2018)"},{"id":"TV-Primestream_58_224","title":"Indiana Jones 5 (2022)"},{"id":"TV-Primestream_58_225","title":"Troya (2019)"},{"id":"TV-Primestream_58_226","title":"Los descendientes (2015)"},{"id":"TV-Primestream_58_227","title":"La fiesta de las salchichas (2016)"},{"id":"TV-Primestream_58_228","title":"Rápida y mortal (1995)"},{"id":"TV-Primestream_58_229","title":"Alfa (2016)"},{"id":"TV-Primestream_58_230","title":"The Karate Kid (2010)"},{"id":"TV-Primestream_58_231","title":"El reino de los monos (2015)"},{"id":"TV-Primestream_58_232","title":"Mad Max: Salvajes de autopista (1979)"},{"id":"TV-Primestream_58_233","title":"Las mil caras de Dunjia (2017)"},{"id":"TV-Primestream_58_234","title":"Monkeybone (2001)"},{"id":"TV-Primestream_58_235","title":"Okja (2017)"},{"id":"TV-Primestream_58_236","title":"Max (2015)"},{"id":"TV-Primestream_58_237","title":"Viaje al centro de la Tierra 2: La isla misteriosa (2012)"},{"id":"TV-Primestream_58_238","title":"El mexicano (2003)"},{"id":"TV-Primestream_58_239","title":"Liberad a Willy (1993)"},{"id":"TV-Primestream_58_240","title":"Kicks (2016)"},{"id":"TV-Primestream_58_241","title":"Hansel & Gretel: Cazadores de brujas (2013)"},{"id":"TV-Primestream_58_242","title":"Cocodrilo Dundee II (1988)"},{"id":"TV-Primestream_58_243","title":"Campamento alienígena (2019)"},{"id":"TV-Primestream_58_244","title":"Blancanieves y la leyenda del cazador (2012)"},{"id":"TV-Primestream_58_245","title":"Nancy Drew y la Escalera Escondida (2019)"},{"id":"TV-Primestream_58_246","title":"Adèle y el misterio de la momia (2010)"},{"id":"TV-Primestream_58_247","title":"Escalofrío (1978)"},{"id":"TV-Primestream_58_248","title":"Beowulf (2007)"},{"id":"TV-Primestream_58_249","title":"Appaloosa (2008)"},{"id":"TV-Primestream_58_250","title":"The Mummy (La momia) (1999)"},{"id":"TV-Primestream_58_251","title":"La Sirenita (2018)"},{"id":"TV-Primestream_58_252","title":"El arte de la guerra (2000)"},{"id":"TV-Primestream_58_253","title":"Interestelar (2014)"},{"id":"TV-Primestream_58_254","title":"Charlie y la fábrica de chocolate (2005)"},{"id":"TV-Primestream_58_255","title":"El rey Arturo (2004)"},{"id":"TV-Primestream_58_256","title":"El juego de Ender (2013)"},{"id":"TV-Primestream_58_257","title":"The Aeronauts (2019)"},{"id":"TV-Primestream_58_258","title":"Dragonheart 4: Corazón de fuego (2017)"},{"id":"TV-Primestream_58_259","title":"El desafío (The Walk) (2015)"}]}}